<?xml version="1.0" encoding="latin1"?>
<EXTENSION VERSION="20.1">
<LOGICS>
<LOGICITEM NAME="Extents">
	<STATE NAME="Chart2dViewerExtentsState" VERSION="20.1">
	<PROPERTIES>
	<PROPERTY NAME="XAxisMin">
	<VALUE>-37.00215744643262</VALUE>
	</PROPERTY>
	<PROPERTY NAME="XAxisMax">
	<VALUE>121.3770063855142</VALUE>
	</PROPERTY>
	<PROPERTY NAME="YAxisMin">
	<VALUE>171.3798998204655</VALUE>
	</PROPERTY>
	<PROPERTY NAME="YAxisMax">
	<VALUE>488.7976728781852</VALUE>
	</PROPERTY>
	</PROPERTIES>
	</STATE>
</LOGICITEM>
</LOGICS>
</EXTENSION>
